sync_fifo.v
module sync_fifo #(
    parameter DATA_WIDTH = 8,
    parameter FIFO_DEPTH = 16
)(
    input  wire                  clk,
    input  wire                  reset,

    input  wire                  wr_en,
    input  wire                  rd_en,
    input  wire [DATA_WIDTH-1:0] wr_data,

    output reg  [DATA_WIDTH-1:0] rd_data,
    output wire                  full,
    output wire                  empty
);

    // FIFO memory
    reg [DATA_WIDTH-1:0] mem [0:FIFO_DEPTH-1];

    // Pointers
    reg [3:0] wr_ptr;
    reg [3:0] rd_ptr;

    // Number of stored elements
    reg [4:0] count;

    // Empty and full conditions
    assign empty = (count == 0);
    assign full  = (count == FIFO_DEPTH);

    always @(posedge clk) begin

        if (reset) begin
            wr_ptr  <= 4'b0000;
            rd_ptr  <= 4'b0000;
            count   <= 5'b00000;
            rd_data <= {DATA_WIDTH{1'b0}};
        end

        else begin

            // Write operation
            if (wr_en && !full) begin
                mem[wr_ptr] <= wr_data;
                wr_ptr <= wr_ptr + 1'b1;
            end

            // Read operation
            if (rd_en && !empty) begin
                rd_data <= mem[rd_ptr];
                rd_ptr <= rd_ptr + 1'b1;
            end

            // Update FIFO count
            case ({wr_en && !full, rd_en && !empty})

                2'b10: count <= count + 1'b1; // Write only
                2'b01: count <= count - 1'b1; // Read only
                2'b11: count <= count;        // Read and write
                default: count <= count;      // No operation

            endcase
        end
    end

endmodule

sync_fifo_tb.v
`timescale 1ns/1ps

module sync_fifo_tb;

    parameter DATA_WIDTH = 8;
    parameter FIFO_DEPTH = 16;

    // Testbench signals
    reg clk;
    reg reset;
    reg wr_en;
    reg rd_en;
    reg [DATA_WIDTH-1:0] wr_data;

    wire [DATA_WIDTH-1:0] rd_data;
    wire full;
    wire empty;

    // ------------------------------------------------
    // DUT: Device Under Test
    // ------------------------------------------------

    sync_fifo #(
        .DATA_WIDTH(DATA_WIDTH),
        .FIFO_DEPTH(FIFO_DEPTH)
    ) dut (
        .clk(clk),
        .reset(reset),
        .wr_en(wr_en),
        .rd_en(rd_en),
        .wr_data(wr_data),
        .rd_data(rd_data),
        .full(full),
        .empty(empty)
    );

    // ------------------------------------------------
    // Clock Generation
    // 10 ns clock period
    // ------------------------------------------------

    always #5 clk = ~clk;

    // ------------------------------------------------
    // VCD Waveform Generation
    // ------------------------------------------------

    initial begin
        $dumpfile("sync_fifo.vcd");
        $dumpvars(0, sync_fifo_tb);
    end

    // ------------------------------------------------
    // Main Test
    // ------------------------------------------------

    initial begin

        // Initialize signals
        clk     = 0;
        reset   = 1;
        wr_en   = 0;
        rd_en   = 0;
        wr_data = 0;

        // ============================================
        // TEST 1: RESET
        // ============================================

        #12;
        reset = 0;

        $display("--------------------------------------");
        $display("RESET COMPLETED");
        $display("--------------------------------------");

        // ============================================
        // TEST 2: WRITE FOUR VALUES
        // ============================================

        @(negedge clk);

        wr_en   = 1;
        rd_en   = 0;
        wr_data = 8'hA1;

        @(negedge clk);
        wr_data = 8'hB2;

        @(negedge clk);
        wr_data = 8'hC3;

        @(negedge clk);
        wr_data = 8'hD4;

        @(negedge clk);
        wr_en = 0;

        $display("TEST 2: FOUR VALUES WRITTEN");
        $display("A1 -> B2 -> C3 -> D4");

        // ============================================
        // TEST 3: READ TWO VALUES
        // ============================================

        @(negedge clk);

        rd_en = 1;

        @(negedge clk);
        rd_en = 0;

        @(negedge clk);
        rd_en = 1;

        @(negedge clk);
        rd_en = 0;

        $display("TEST 3: TWO VALUES READ");
        $display("Expected order: A1 -> B2");

        // ============================================
        // TEST 4: SIMULTANEOUS READ AND WRITE
        // ============================================

        @(negedge clk);

        wr_en   = 1;
        rd_en   = 1;
        wr_data = 8'hE5;

        @(negedge clk);

        wr_en = 0;
        rd_en = 0;

        $display("TEST 4: SIMULTANEOUS READ/WRITE COMPLETED");

        // ============================================
        // TEST 5: FILL FIFO COMPLETELY
        // ============================================

        @(negedge clk);

        wr_en = 1;
        rd_en = 0;

        wr_data = 8'h01;

        @(negedge clk);
        wr_data = 8'h02;

        @(negedge clk);
        wr_data = 8'h03;

        @(negedge clk);
        wr_data = 8'h04;

        @(negedge clk);
        wr_data = 8'h05;

        @(negedge clk);
        wr_data = 8'h06;

        @(negedge clk);
        wr_data = 8'h07;

        @(negedge clk);
        wr_data = 8'h08;

        @(negedge clk);
        wr_data = 8'h09;

        @(negedge clk);
        wr_data = 8'h0A;

        @(negedge clk);
        wr_data = 8'h0B;

        @(negedge clk);
        wr_data = 8'h0C;

        @(negedge clk);
        wr_data = 8'h0D;

        @(negedge clk);
        wr_data = 8'h0E;

        @(negedge clk);
        wr_data = 8'h0F;

        @(negedge clk);
        wr_data = 8'h10;

        @(negedge clk);

        wr_en = 0;

        // ============================================
        // CHECK FULL CONDITION
        // ============================================

        if (full == 1'b1)
            $display("TEST 5: FIFO FULL CONDITION -> PASS");
        else
            $display("TEST 5: FIFO FULL CONDITION -> FAIL");

// ============================================
// TEST 6: TRY TO WRITE WHEN FIFO IS FULL
// ============================================

@(negedge clk);

wr_en   = 1;
rd_en   = 0;
wr_data = 8'hFF;

@(posedge clk);
#1;

// FIFO should still be full
// because writing must be blocked when full

if (full == 1'b1)
    $display("TEST 6: WRITE WHILE FULL -> PASS");
else
    $display("TEST 6: WRITE WHILE FULL -> FAIL");

wr_en = 0;


        // ============================================
        // TEST 7: READ ALL DATA
        // ============================================

        @(negedge clk);

        rd_en = 1;

        repeat (16) begin
            @(negedge clk);
        end

        rd_en = 0;

        // ============================================
        // CHECK EMPTY CONDITION
        // ============================================

        @(negedge clk);

        if (empty == 1'b1)
            $display("TEST 7: FIFO EMPTY CONDITION -> PASS");
        else
            $display("TEST 7: FIFO EMPTY CONDITION -> FAIL");

        // ============================================
        // END SIMULATION
        // ============================================

        #20;

        $display("--------------------------------------");
        $display("FIFO SIMULATION COMPLETED");
        $display("--------------------------------------");

        $finish;

    end

    // ------------------------------------------------
    // Terminal Monitor
    // ------------------------------------------------

    initial begin

        $monitor(
            "Time=%0t | Reset=%b | WR=%b | RD=%b | Data_In=%h | Data_Out=%h | Full=%b | Empty=%b",
            $time,
            reset,
            wr_en,
            rd_en,
            wr_data,
            rd_data,
            full,
            empty
        );

    end

endmodule

sync_fifo.vcd
$date
	Wed Aug 26 03:11:42 2026
$end
$version
	Icarus Verilog
$end
$timescale
	1ps
$end
$scope module sync_fifo_tb $end
$var wire 8 ! rd_data [7:0] $end
$var wire 1 " full $end
$var wire 1 # empty $end
$var parameter 32 $ DATA_WIDTH $end
$var parameter 32 % FIFO_DEPTH $end
$var reg 1 & clk $end
$var reg 1 ' rd_en $end
$var reg 1 ( reset $end
$var reg 8 ) wr_data [7:0] $end
$var reg 1 * wr_en $end
$scope module dut $end
$var wire 1 & clk $end
$var wire 1 ' rd_en $end
$var wire 1 ( reset $end
$var wire 8 + wr_data [7:0] $end
$var wire 1 * wr_en $end
$var wire 1 " full $end
$var wire 1 # empty $end
$var parameter 32 , DATA_WIDTH $end
$var parameter 32 - FIFO_DEPTH $end
$var reg 5 . count [4:0] $end
$var reg 8 / rd_data [7:0] $end
$var reg 4 0 rd_ptr [3:0] $end
$var reg 4 1 wr_ptr [3:0] $end
$upscope $end
$upscope $end
$enddefinitions $end
$comment Show the parameter values. $end
$dumpall
b10000 -
b1000 ,
b10000 %
b1000 $
$end
#0
$dumpvars
bx 1
bx 0
bx /
bx .
b0 +
0*
b0 )
1(
0'
0&
x#
x"
bx !
$end
#5000
b0 !
b0 /
1#
0"
b0 .
b0 0
b0 1
1&
#10000
0&
#12000
0(
#15000
1&
#20000
b10100001 )
b10100001 +
1*
0&
#25000
0#
b1 .
b1 1
1&
#30000
b10110010 )
b10110010 +
0&
#35000
b10 .
b10 1
1&
#40000
b11000011 )
b11000011 +
0&
#45000
b11 .
b11 1
1&
#50000
b11010100 )
b11010100 +
0&
#55000
b100 .
b100 1
1&
#60000
0*
0&
#65000
1&
#70000
1'
0&
#75000
b11 .
b1 0
b10100001 !
b10100001 /
1&
#80000
0'
0&
#85000
1&
#90000
1'
0&
#95000
b10 .
b10 0
b10110010 !
b10110010 /
1&
#100000
0'
0&
#105000
1&
#110000
b11100101 )
b11100101 +
1'
1*
0&
#115000
b11 0
b11000011 !
b11000011 /
b101 1
1&
#120000
0'
0*
0&
#125000
1&
#130000
b1 )
b1 +
1*
0&
#135000
b11 .
b110 1
1&
#140000
b10 )
b10 +
0&
#145000
b100 .
b111 1
1&
#150000
b11 )
b11 +
0&
#155000
b101 .
b1000 1
1&
#160000
b100 )
b100 +
0&
#165000
b110 .
b1001 1
1&
#170000
b101 )
b101 +
0&
#175000
b111 .
b1010 1
1&
#180000
b110 )
b110 +
0&
#185000
b1000 .
b1011 1
1&
#190000
b111 )
b111 +
0&
#195000
b1001 .
b1100 1
1&
#200000
b1000 )
b1000 +
0&
#205000
b1010 .
b1101 1
1&
#210000
b1001 )
b1001 +
0&
#215000
b1011 .
b1110 1
1&
#220000
b1010 )
b1010 +
0&
#225000
b1100 .
b1111 1
1&
#230000
b1011 )
b1011 +
0&
#235000
b1101 .
b0 1
1&
#240000
b1100 )
b1100 +
0&
#245000
b1110 .
b1 1
1&
#250000
b1101 )
b1101 +
0&
#255000
b1111 .
b10 1
1&
#260000
b1110 )
b1110 +
0&
#265000
1"
b10000 .
b11 1
1&
#270000
b1111 )
b1111 +
0&
#275000
1&
#280000
b10000 )
b10000 +
0&
#285000
1&
#290000
0*
0&
#295000
1&
#300000
b11111111 )
b11111111 +
1*
0&
#305000
1&
#306000
0*
#310000
1'
0&
#315000
0"
b1111 .
b100 0
b11010100 !
b11010100 /
1&
#320000
0&
#325000
b1110 .
b101 0
b11100101 !
b11100101 /
1&
#330000
0&
#335000
b1101 .
b110 0
b1 !
b1 /
1&
#340000
0&
#345000
b1100 .
b111 0
b10 !
b10 /
1&
#350000
0&
#355000
b1011 .
b1000 0
b11 !
b11 /
1&
#360000
0&
#365000
b1010 .
b1001 0
b100 !
b100 /
1&
#370000
0&
#375000
b1001 .
b1010 0
b101 !
b101 /
1&
#380000
0&
#385000
b1000 .
b1011 0
b110 !
b110 /
1&
#390000
0&
#395000
b111 .
b1100 0
b111 !
b111 /
1&
#400000
0&
#405000
b110 .
b1101 0
b1000 !
b1000 /
1&
#410000
0&
#415000
b101 .
b1110 0
b1001 !
b1001 /
1&
#420000
0&
#425000
b100 .
b1111 0
b1010 !
b1010 /
1&
#430000
0&
#435000
b11 .
b0 0
b1011 !
b1011 /
1&
#440000
0&
#445000
b10 .
b1 0
b1100 !
b1100 /
1&
#450000
0&
#455000
b1 .
b10 0
b1101 !
b1101 /
1&
#460000
0&
#465000
1#
b0 .
b11 0
b1110 !
b1110 /
1&
#470000
0'
0&
